tac_test_package/AutoTAC.py
tac_test_package/TAC.py
tac_test_package/__init__.py
tac_test_package/models/AutoTAC.py
tac_test_package/models/TAC.py
tac_test_package/models/__init_.py
tac_test_package/models/__init__.py
tac_test_package/models/run/__init__.py
tac_test_package/models/run/multiple.py
tac_test_package/models/run/single.py
tac_test_package/models/utils/__init__.py
tac_test_package/models/utils/format_save.py
tac_test_package/models/utils/metrics.py
tac_test_package/models/utils/plots.py
tac_test_package/run/__init__.py
tac_test_package/run/multiple.py
tac_test_package/run/single.py
tac_test_package/utils/__init__.py
tac_test_package/utils/format_save.py
tac_test_package/utils/metrics.py
tac_test_package/utils/plots.py
tac_test_package-0.1.3.dist-info/LICENSE
tac_test_package-0.1.3.dist-info/METADATA
tac_test_package-0.1.3.dist-info/WHEEL
tac_test_package-0.1.3.dist-info/top_level.txt
tac_test_package-0.1.3.dist-info/RECORD
