Metadata-Version: 2.1
Name: tac-test-package
Version: 0.1.3
Summary: A python library
Home-page: https://github.com/conect2ai/
Author: Miguel
Author-email: miguel.amaral.111@ufrn.edu.com
Keywords: Annomaly Detection
Classifier: License :: OSI Approved :: MIT License
Classifier: Programming Language :: Python :: 3
License-File: LICENSE
Requires-Dist: numpy
Requires-Dist: pandas
Requires-Dist: matplotlib
Requires-Dist: seaborn
Requires-Dist: ipython
Requires-Dist: scikit-learn
